CHANGES.txt
LICENSE.txt
MANIFEST.in
README.rst
changelog
setup.cfg
setup.py
RedisORM.egg-info/PKG-INFO
RedisORM.egg-info/SOURCES.txt
RedisORM.egg-info/dependency_links.txt
RedisORM.egg-info/requires.txt
RedisORM.egg-info/top_level.txt
RedisORM.egg-info/zip-safe
docs/index.rst
redisORM/__init__.py
redisORM/redis_model.py