Metadata-Version: 1.1
Name: RedisORM
Version: 0.2.0
Summary: Simple little ORM thing for Redis
Home-page: https://github.com/JoshAshby/pyRedisORM/
Author: Joshua P Ashby
Author-email: joshuaashby@joshashby.com
License: MIT
Keywords: redis orm database
Platform: UNKNOWN
Classifier: Development Status :: 3 - Alpha
Classifier: Intended Audience :: Developers
Classifier: License :: OSI Approved :: MIT License
Classifier: Programming Language :: Python :: 2.7
